README.txt
setup.cfg
setup.py
docs/HISTORY.txt
docs/INSTALL.txt
docs/LICENSE.GPL
docs/LICENSE.txt
p4a/__init__.py
p4a.videoembed.egg-info/PKG-INFO
p4a.videoembed.egg-info/SOURCES.txt
p4a.videoembed.egg-info/dependency_links.txt
p4a.videoembed.egg-info/entry_points.txt
p4a.videoembed.egg-info/namespace_packages.txt
p4a.videoembed.egg-info/not-zip-safe
p4a.videoembed.egg-info/requires.txt
p4a.videoembed.egg-info/top_level.txt
p4a/videoembed/__init__.py
p4a/videoembed/_cache.py
p4a/videoembed/configure.zcml
p4a/videoembed/converters.py
p4a/videoembed/interfaces.py
p4a/videoembed/registry.py
p4a/videoembed/tests.py
p4a/videoembed/utils.py
p4a/videoembed/providers/__init__.py
p4a/videoembed/providers/bliptv.py
p4a/videoembed/providers/bliptv.zcml
p4a/videoembed/providers/configure.zcml
p4a/videoembed/providers/dailymotion.py
p4a/videoembed/providers/dailymotion.zcml
p4a/videoembed/providers/flash.py
p4a/videoembed/providers/flash.zcml
p4a/videoembed/providers/googlevideo.py
p4a/videoembed/providers/googlevideo.zcml
p4a/videoembed/providers/revver.py
p4a/videoembed/providers/revver.zcml
p4a/videoembed/providers/ustreamtv.py
p4a/videoembed/providers/ustreamtv.zcml
p4a/videoembed/providers/youtube.py
p4a/videoembed/providers/youtube.zcml