Metadata-Version: 1.0
Name: p4a.videoembed
Version: 1.3
Summary: A registry and adapters for converting urls for various video sharing sites into embed codes.
Home-page: http://www.plone4artists.org/svn/projects/p4a.videoembed
Author: Alec Mitchell
Author-email: apm13@columbia.edu
License: GPL
Keywords: Embedded Video Plone
Platform: UNKNOWN
Classifier: Framework :: Zope3
Classifier: Programming Language :: Python
Classifier: License :: OSI Approved :: GNU General Public License (GPL)
Classifier: Topic :: Software Development :: Libraries :: Python Modules
Classifier: Topic :: Multimedia :: Video
